{
  "_format": "hh-sol-cache-2",
  "files": {
    "E:\\Projects\\Project\\drivego-blockchain\\contracts\\UserDetails.sol": {
      "lastModificationDate": 1684389327756,
      "contentHash": "e527cf7eba0a2e4710ec2b11bdea831a",
      "sourceName": "contracts/UserDetails.sol",
      "solcConfig": {
        "version": "0.8.17",
        "settings": {
          "optimizer": {
            "enabled": true,
            "runs": 200
          },
          "outputSelection": {
            "*": {
              "*": [
                "abi",
                "evm.bytecode",
                "evm.deployedBytecode",
                "evm.methodIdentifiers",
                "metadata"
              ],
              "": [
                "ast"
              ]
            }
          }
        }
      },
      "imports": [],
      "versionPragmas": [
        "0.8.17"
      ],
      "artifacts": [
        "UserDetails"
      ]
    }
  }
}
